README.md
setup.py
pandas_mapper/__init__.py
pandas_mapper/pandas_mapper.py
pandas_mapper/version.py
pandas_mapper.egg-info/PKG-INFO
pandas_mapper.egg-info/SOURCES.txt
pandas_mapper.egg-info/dependency_links.txt
pandas_mapper.egg-info/requires.txt
pandas_mapper.egg-info/top_level.txt