Metadata-Version: 2.1
Name: pandas-mapper
Version: 0.1.3
Summary: Pandas Mapper
Home-page: https://github.com/inside-track/pandas-mapper
Author: Sterling Paramore
Author-email: sterling.paramore@insidetrack.com
License: MIT
Keywords: etl data workflows pandas
Platform: UNKNOWN
Classifier: Development Status :: 3 - Alpha
Classifier: Intended Audience :: Developers
Classifier: Topic :: Software Development :: Libraries :: Python Modules
Classifier: License :: OSI Approved :: MIT License
Classifier: Programming Language :: Python :: 3
Classifier: Programming Language :: Python :: 3.6
Requires-Python: >=3
Provides-Extra: dev
Provides-Extra: test
